lightning_enable_mcp/__init__.py
lightning_enable_mcp/budget.py
lightning_enable_mcp/budget_service.py
lightning_enable_mcp/config.py
lightning_enable_mcp/l402_client.py
lightning_enable_mcp/license.py
lightning_enable_mcp/nwc_wallet.py
lightning_enable_mcp/opennode_wallet.py
lightning_enable_mcp/price_service.py
lightning_enable_mcp/py.typed
lightning_enable_mcp/server.py
lightning_enable_mcp/strike_wallet.py
lightning_enable_mcp/tools/__init__.py
lightning_enable_mcp/tools/access_resource.py
lightning_enable_mcp/tools/budget.py
lightning_enable_mcp/tools/budget_status.py
lightning_enable_mcp/tools/license.py
lightning_enable_mcp/tools/pay_challenge.py
lightning_enable_mcp/tools/pay_invoice.py
lightning_enable_mcp/tools/wallet.py
lightning_enable_mcp-1.3.1.dist-info/METADATA
lightning_enable_mcp-1.3.1.dist-info/WHEEL
lightning_enable_mcp-1.3.1.dist-info/entry_points.txt
lightning_enable_mcp-1.3.1.dist-info/licenses/LICENSE
lightning_enable_mcp-1.3.1.dist-info/RECORD
