Metadata-Version: 2.4
Name: lightning-enable-mcp
Version: 1.3.1
Summary: MCP server for L402 Lightning payments - access paid APIs with AI agents
Project-URL: Homepage, https://lightningenable.com
Project-URL: Documentation, https://github.com/refinedelement/lightning-enable-mcp
Project-URL: Repository, https://github.com/refinedelement/lightning-enable-mcp
Project-URL: Issues, https://github.com/refinedelement/lightning-enable-mcp/issues
Author-email: Lightning Enable <support@lightningenable.com>
License-Expression: MIT
License-File: LICENSE
Keywords: agents,ai,bitcoin,l402,lightning,lsat,mcp,model-context-protocol,nostr,nwc,payments
Classifier: Development Status :: 4 - Beta
Classifier: Intended Audience :: Developers
Classifier: License :: OSI Approved :: MIT License
Classifier: Operating System :: OS Independent
Classifier: Programming Language :: Python :: 3
Classifier: Programming Language :: Python :: 3.10
Classifier: Programming Language :: Python :: 3.11
Classifier: Programming Language :: Python :: 3.12
Classifier: Topic :: Internet :: WWW/HTTP
Classifier: Topic :: Office/Business :: Financial :: Point-Of-Sale
Classifier: Topic :: Software Development :: Libraries :: Python Modules
Requires-Python: >=3.10
Requires-Dist: aiohttp>=3.9.0
Requires-Dist: bech32>=1.2.0
Requires-Dist: bolt11>=2.0.0
Requires-Dist: cryptography>=41.0.0
Requires-Dist: httpx>=0.25.0
Requires-Dist: mcp>=1.0.0
Requires-Dist: pydantic>=2.0.0
Requires-Dist: secp256k1>=0.14.0
Requires-Dist: websockets>=12.0
Provides-Extra: dev
Requires-Dist: mypy>=1.0.0; extra == 'dev'
Requires-Dist: pytest-asyncio>=0.21.0; extra == 'dev'
Requires-Dist: pytest-cov>=4.0.0; extra == 'dev'
Requires-Dist: pytest>=7.0.0; extra == 'dev'
Requires-Dist: ruff>=0.1.0; extra == 'dev'
